[
    {
        "Id": 1,
         "Nombre": "Nathalia",
         "Apellido": "Bevacqua",
         "Email": "email@gmail.com",
         "password": "admin",
         "Categoria": "admin",
         "Imagen": "perfil",
         "userImage":""
    },
    {
        "Id": 2,
         "Nombre": "Lautaro",
         "Apellido": "Garcia",
         "Email": "email@gmail.com",
         "password": "admin",
         "Categoria": "Admin",
         "Imagen": "perfil",
         "userImage": ""
    },
    {
        "Id": 3,
         "Nombre": "Jairo",
         "Apellido": "Abarca",
         "Email": "email@gmail.com",
         "password": "admin",
         "Categoria": "admin",
         "Imagen": "perfil",
         "userImage": ""
    }
]